hdproc/HDP.py
hdproc/__init__.py
hdproc/text_prep.py
hdproc-0.38.dist-info/LICENSE
hdproc-0.38.dist-info/METADATA
hdproc-0.38.dist-info/WHEEL
hdproc-0.38.dist-info/top_level.txt
hdproc-0.38.dist-info/RECORD
